Textcutpackage/__init__.py
Textcutpackage/textcuts.py
TextCutUps-0.0.4.dist-info/LICENSE.txt
TextCutUps-0.0.4.dist-info/METADATA
TextCutUps-0.0.4.dist-info/WHEEL
TextCutUps-0.0.4.dist-info/top_level.txt
TextCutUps-0.0.4.dist-info/RECORD
