Metadata-Version: 2.1
Name: TextCutUps
Version: 0.0.4
Summary: A package that helps cut up text for creative writers
Home-page: https://github.com/users/lukedevereux/projects/1
Author: Luke Devereux
Author-email: 
License: UNKNOWN
Platform: UNKNOWN
Classifier: Programming Language :: Python :: 3
Classifier: License :: OSI Approved :: MIT License
Classifier: Operating System :: OS Independent
Requires-Python: >=3.6
License-File: LICENSE.txt
